django_graphene_permissions/__init__.py
django_graphene_permissions/__version__.py
django_graphene_permissions/decorators.py
django_graphene_permissions/exceptions.py
django_graphene_permissions/permissions.py
django_graphene_permissions_redux-1.0.0.dist-info/LICENSE
django_graphene_permissions_redux-1.0.0.dist-info/METADATA
django_graphene_permissions_redux-1.0.0.dist-info/WHEEL
django_graphene_permissions_redux-1.0.0.dist-info/top_level.txt
django_graphene_permissions_redux-1.0.0.dist-info/RECORD
