Metadata-Version: 2.1
Name: django-graphene-permissions-redux
Version: 1.0.0
Summary: DRF like permission system for django graphene
Home-page: https://github.com/mdettelson/django-graphene-permissions-redux
Author: Max Ettelson
Author-email: mdettelson@gmail.com
License: BSD
Classifier: License :: OSI Approved :: BSD License
Classifier: Programming Language :: Python
Classifier: Programming Language :: Python :: 3
Classifier: Framework :: Django
Classifier: Operating System :: OS Independent
License-File: LICENSE
